bottle_jsonschema.py
bottle_jsonschema-0.0.1.dist-info/METADATA
bottle_jsonschema-0.0.1.dist-info/RECORD
bottle_jsonschema-0.0.1.dist-info/WHEEL
bottle_jsonschema-0.0.1.dist-info/top_level.txt
