Metadata-Version: 2.1
Name: bottle-jsonschema
Version: 0.0.1
Summary: Automatic JSON schema validation for Bottle
Home-page: https://github.com/Hubro/bottle-jsonschema
Author: Tomas Sandven
Author-email: tomas191191@gmail.com
License: UNKNOWN
Platform: UNKNOWN
Classifier: Programming Language :: Python :: 3
Classifier: License :: OSI Approved :: MIT License
Classifier: Operating System :: OS Independent
